swem/__init__.py
swem/download.py
swem/models.py
swem/version.py
swem-0.4.1.dist-info/LICENSE
swem-0.4.1.dist-info/METADATA
swem-0.4.1.dist-info/WHEEL
swem-0.4.1.dist-info/top_level.txt
swem-0.4.1.dist-info/RECORD
