Metadata-Version: 2.1
Name: swem
Version: 0.4.1
Summary: A portable document embedding using SWEM.
Home-page: https://github.com/yutayamazaki/swem
Author: Yuta Yamazaki
Author-email: yu.yamazakii@gmail.com
Maintainer: Yuta Yamazaki
Maintainer-email: yu.yamazakii@gmail.com
License: MIT
Keywords: swem nlp python
Platform: UNKNOWN
Requires-Dist: gensim
Requires-Dist: numpy
Requires-Dist: requests
